client/__init__.py
client/add_contact.py
client/database.py
client/del_contact.py
client/main_window.py
client/main_window_conv.py
client/start_dialog.py
client/transport.py
common/__init__.py
common/descryptors.py
common/errors.py
common/metaclasses.py
common/utils.py
common/variables.py
log/__init__.py
log/config_client_log.py
log/config_server_log.py
log/decorator_log.py
ok_client_messenger-0.1.dist-info/METADATA
ok_client_messenger-0.1.dist-info/WHEEL
ok_client_messenger-0.1.dist-info/top_level.txt
ok_client_messenger-0.1.dist-info/RECORD
