Metadata-Version: 2.1
Name: ok-client-messenger
Version: 0.1
Summary: ok_client_messenger
Author: Oleg Krechetov
Author-email: kr.oleg@gmail.com
License: UNKNOWN
Platform: UNKNOWN
Requires-Dist: PyQt5
Requires-Dist: sqlalchemy
Requires-Dist: pycryptodome
Requires-Dist: pycryptodomex
